redashAPI/__init__.py
redashAPI/client.py
redash_api_client-0.3.0.dist-info/LICENSE
redash_api_client-0.3.0.dist-info/METADATA
redash_api_client-0.3.0.dist-info/WHEEL
redash_api_client-0.3.0.dist-info/top_level.txt
redash_api_client-0.3.0.dist-info/RECORD
